crop_yolo_v8/__init__.py
crop_yolo_v8/main.py
crop_yolo_v8-1.1.1.dist-info/METADATA
crop_yolo_v8-1.1.1.dist-info/WHEEL
crop_yolo_v8-1.1.1.dist-info/entry_points.txt
crop_yolo_v8-1.1.1.dist-info/RECORD
